squid/__init__.py
squid/impress.py
squid/mave.py
squid/mutagenizer.py
squid/predictor.py
squid/surrogate_zoo.py
squid/utils.py
squid_nn-0.4.8.dist-info/licenses/LICENSE
squid_nn-0.4.8.dist-info/METADATA
squid_nn-0.4.8.dist-info/WHEEL
squid_nn-0.4.8.dist-info/top_level.txt
squid_nn-0.4.8.dist-info/RECORD
