Metadata-Version: 2.4
Name: squid-nn
Version: 0.4.8
Summary: SQUID is a TensorFlow package to interpret sequence-based deep learning models for regulatory genomics data with domain-specific surrogate models.
Author: Evan Seitz
Author-email: evan.e.seitz@gmail.com
Classifier: Programming Language :: Python :: 3
Classifier: License :: OSI Approved :: MIT License
Classifier: Operating System :: OS Independent
Requires-Python: >=3.7.2
License-File: LICENSE
Requires-Dist: numpy
Requires-Dist: matplotlib>=3.2.0
Requires-Dist: pandas
Requires-Dist: tqdm
Dynamic: author
Dynamic: author-email
Dynamic: classifier
Dynamic: license-file
Dynamic: requires-dist
Dynamic: requires-python
Dynamic: summary
